LICENSE
MANIFEST.in
README.md
setup.cfg
setup.py
pyjo/__init__.py
pyjo/exceptions.py
pyjo/model.py
pyjo.egg-info/PKG-INFO
pyjo.egg-info/SOURCES.txt
pyjo.egg-info/dependency_links.txt
pyjo.egg-info/requires.txt
pyjo.egg-info/top_level.txt
pyjo/fields/__init__.py
pyjo/fields/datetimefield.py
pyjo/fields/enumfield.py
pyjo/fields/field.py
pyjo/fields/listfield.py
pyjo/fields/mapfield.py
pyjo/fields/rangefield.py
pyjo/fields/regexfield.py
tests/__init__.py
tests/model_test.py
tests/fields/__init__.py
tests/fields/datefield_test.py
tests/fields/enumfield_test.py
tests/fields/listfield_test.py
tests/fields/mapfield_test.py
tests/fields/rangefield_test.py
tests/fields/regexfield_test.py