Metadata-Version: 1.1
Name: pyjo
Version: 3.1.1
Summary: Python JSON Objects
Home-page: https://github.com/marcopaz/pyjo
Author: Marco Pazzaglia
Author-email: marco@pazzaglia.me
License: UNKNOWN
Download-URL: https://github.com/marcopaz/pyjo/archive/3.1.1.tar.gz
Platform: UNKNOWN
